napari_detect_spots/__init__.py
napari_detect_spots/_widget.py
napari_detect_spots/napari.yaml
napari_detect_spots/_tests/__init__.py
napari_detect_spots/_tests/test_widget.py
test_detect_spots-0.0.1.dist-info/LICENSE
test_detect_spots-0.0.1.dist-info/METADATA
test_detect_spots-0.0.1.dist-info/WHEEL
test_detect_spots-0.0.1.dist-info/entry_points.txt
test_detect_spots-0.0.1.dist-info/top_level.txt
test_detect_spots-0.0.1.dist-info/RECORD
